<?xml version="1.0" encoding="UTF-8"?>
<taglib xmlns="http://java.sun.com/xml/ns/j2ee" xmlns:xsi="http://www.w3.org/2001/XMLSchema-instance" xsi:schemaLocation="http://java.sun.com/xml/ns/j2ee web-jsptaglibrary_2_0.xsd" version="2.0">	
	<tlib-version>2.0</tlib-version>
	<short-name>ct</short-name>
	<uri>http://ludesoft.com/jsp/tag/customtag</uri>
	<tag>
		<name>content</name>
		<tag-class>com.lude.sms.tag.ContextTag</tag-class>
		<attribute>
			<name>title</name>
			<required>true</required>
		</attribute>
		<attribute>
			<name>height</name>
			<required>false</required>
		</attribute>
	</tag>
	<tag>
		<name>pms</name>
		<tag-class>com.lude.sms.tag.PermissionTag</tag-class>
		<attribute>
			<name>name</name>
			<required>true</required>
		</attribute>
	</tag>	
</taglib>
